{
  "content": [
    {
      "content": null,
      "created": "2025-10-26T16:04:11.262684Z",
      "format": null,
      "hash": null,
      "hash_algorithm": null,
      "last_modified": "2024-03-17T08:35:48.417832Z",
      "mimetype": null,
      "name": "C2_W4_Decision_Tree_with_Markdown.ipynb",
      "path": "Machine Learning Specialization\\2. Advanced Learning Algorithm\\Week 4\\bkup/C2_W4_Decision_Tree_with_Markdown.ipynb",
      "size": 42544,
      "type": "notebook",
      "writable": true
    },
    {
      "content": null,
      "created": "2025-10-26T16:04:11.272676Z",
      "format": null,
      "hash": null,
      "hash_algorithm": null,
      "last_modified": "2024-03-17T08:35:54.326715Z",
      "mimetype": "text/x-python",
      "name": "C2_W4_Decision_Tree_with_Markdown.py",
      "path": "Machine Learning Specialization\\2. Advanced Learning Algorithm\\Week 4\\bkup/C2_W4_Decision_Tree_with_Markdown.py",
      "size": 32125,
      "type": "file",
      "writable": true
    },
    {
      "content": null,
      "created": "2025-10-26T16:04:11.280730Z",
      "format": null,
      "hash": null,
      "hash_algorithm": null,
      "last_modified": "2024-03-17T08:30:00.413064Z",
      "mimetype": null,
      "name": "C2_W4_Lab_01_Decision_Trees.ipynb",
      "path": "Machine Learning Specialization\\2. Advanced Learning Algorithm\\Week 4\\bkup/C2_W4_Lab_01_Decision_Trees.ipynb",
      "size": 13108,
      "type": "notebook",
      "writable": true
    },
    {
      "content": null,
      "created": "2025-10-26T16:04:11.288726Z",
      "format": null,
      "hash": null,
      "hash_algorithm": null,
      "last_modified": "2024-03-17T08:30:03.503611Z",
      "mimetype": "text/x-python",
      "name": "C2_W4_Lab_01_Decision_Trees.py",
      "path": "Machine Learning Specialization\\2. Advanced Learning Algorithm\\Week 4\\bkup/C2_W4_Lab_01_Decision_Trees.py",
      "size": 8480,
      "type": "file",
      "writable": true
    },
    {
      "content": null,
      "created": "2025-10-26T16:04:11.296847Z",
      "format": null,
      "hash": null,
      "hash_algorithm": null,
      "last_modified": "2024-03-17T08:33:40.648534Z",
      "mimetype": null,
      "name": "C2_W4_Lab_02_Tree_Ensemble.ipynb",
      "path": "Machine Learning Specialization\\2. Advanced Learning Algorithm\\Week 4\\bkup/C2_W4_Lab_02_Tree_Ensemble.ipynb",
      "size": 28786,
      "type": "notebook",
      "writable": true
    },
    {
      "content": null,
      "created": "2025-10-26T16:04:11.305833Z",
      "format": null,
      "hash": null,
      "hash_algorithm": null,
      "last_modified": "2024-03-17T08:33:44.548707Z",
      "mimetype": "text/x-python",
      "name": "C2_W4_Lab_02_Tree_Ensemble.py",
      "path": "Machine Learning Specialization\\2. Advanced Learning Algorithm\\Week 4\\bkup/C2_W4_Lab_02_Tree_Ensemble.py",
      "size": 21262,
      "type": "file",
      "writable": true
    }
  ],
  "created": "2025-10-26T16:04:11.260675Z",
  "format": "json",
  "hash": null,
  "hash_algorithm": null,
  "last_modified": "2025-10-26T16:04:11.305833Z",
  "mimetype": null,
  "name": "Machine Learning Specialization\\2. Advanced Learning Algorithm\\Week 4\\bkup",
  "path": "Machine Learning Specialization\\2. Advanced Learning Algorithm\\Week 4\\bkup",
  "size": null,
  "type": "directory",
  "writable": true
}