{
  "content": [
    {
      "content": null,
      "created": "2025-10-26T16:04:10.592122Z",
      "format": null,
      "hash": null,
      "hash_algorithm": null,
      "last_modified": "2024-03-17T08:04:50.578450Z",
      "mimetype": "text/plain",
      "name": "X .txt",
      "path": "Machine Learning Specialization\\2. Advanced Learning Algorithm\\Week 1\\data/X .txt",
      "size": 16000128,
      "type": "file",
      "writable": true
    },
    {
      "content": null,
      "created": "2025-10-26T16:04:10.611123Z",
      "format": null,
      "hash": null,
      "hash_algorithm": null,
      "last_modified": "2024-03-17T08:04:50.578450Z",
      "mimetype": null,
      "name": "X.npy",
      "path": "Machine Learning Specialization\\2. Advanced Learning Algorithm\\Week 1\\data/X.npy",
      "size": 16000128,
      "type": "file",
      "writable": true
    },
    {
      "content": null,
      "created": "2025-10-26T16:04:10.641127Z",
      "format": null,
      "hash": null,
      "hash_algorithm": null,
      "last_modified": "2024-03-17T08:04:50.434089Z",
      "mimetype": null,
      "name": "y.npy",
      "path": "Machine Learning Specialization\\2. Advanced Learning Algorithm\\Week 1\\data/y.npy",
      "size": 5128,
      "type": "file",
      "writable": true
    },
    {
      "content": null,
      "created": "2025-10-26T16:04:10.647127Z",
      "format": null,
      "hash": null,
      "hash_algorithm": null,
      "last_modified": "2024-03-17T08:04:50.434089Z",
      "mimetype": "text/plain",
      "name": "y.txt",
      "path": "Machine Learning Specialization\\2. Advanced Learning Algorithm\\Week 1\\data/y.txt",
      "size": 5128,
      "type": "file",
      "writable": true
    }
  ],
  "created": "2025-10-26T16:04:10.590103Z",
  "format": "json",
  "hash": null,
  "hash_algorithm": null,
  "last_modified": "2025-10-26T16:04:10.647127Z",
  "mimetype": null,
  "name": "Machine Learning Specialization\\2. Advanced Learning Algorithm\\Week 1\\data",
  "path": "Machine Learning Specialization\\2. Advanced Learning Algorithm\\Week 1\\data",
  "size": null,
  "type": "directory",
  "writable": true
}